odoo/addons/ssi_duration_mixin/README.rst
odoo/addons/ssi_duration_mixin/__init__.py
odoo/addons/ssi_duration_mixin/__manifest__.py
odoo/addons/ssi_duration_mixin/menu.xml
odoo/addons/ssi_duration_mixin/models/__init__.py
odoo/addons/ssi_duration_mixin/models/mixin_date_duration.py
odoo/addons/ssi_duration_mixin/models/mixin_datetime_duration.py
odoo/addons/ssi_duration_mixin/static/description/icon.png
odoo14_addon_ssi_duration_mixin-14.0.2.1.0.dist-info/METADATA
odoo14_addon_ssi_duration_mixin-14.0.2.1.0.dist-info/WHEEL
odoo14_addon_ssi_duration_mixin-14.0.2.1.0.dist-info/top_level.txt
odoo14_addon_ssi_duration_mixin-14.0.2.1.0.dist-info/RECORD
